README.md
setup.py
inlimite4ever.egg-info/PKG-INFO
inlimite4ever.egg-info/SOURCES.txt
inlimite4ever.egg-info/dependency_links.txt
inlimite4ever.egg-info/top_level.txt
unlimite4ever/__init__.py
unlimite4ever/ai.py