Metadata-Version: 2.1
Name: inlimite4ever
Version: 2.0
Summary: Im tring to use anything free, unlimite and FAST And also reliable
Home-page: https://github.com/UndrDsk0M/unlimite4ever
Author: UndrDskM = Ehsan vk
Author-email: gamer.good1400@gmail.com
License: UNKNOWN
Platform: UNKNOWN
